Topsis-Paavan-102003738/__init__.py
Topsis-Paavan-102003738/__main__.py
Topsis-Shrey-102183040/__init__.py
Topsis-Shrey-102183040/__main__.py
topsisfile/__init__.py
topsisfile/__main__.py
Topsis_Paavan_102003738-1.0.1.dist-info/METADATA
Topsis_Paavan_102003738-1.0.1.dist-info/WHEEL
Topsis_Paavan_102003738-1.0.1.dist-info/entry_points.txt
Topsis_Paavan_102003738-1.0.1.dist-info/top_level.txt
Topsis_Paavan_102003738-1.0.1.dist-info/RECORD
