Metadata-Version: 2.1
Name: Topsis-Paavan-102003738
Version: 1.0.1
Summary: Calculate topsis score and rank and evaluate.
Home-page: https://github.com/Paavan75/Topsis
Author: Paavan Singh Sayal
Author-email: paavan.sayal@gmail.com
License: MIT
Classifier: License :: OSI Approved :: MIT License
Classifier: Programming Language :: Python :: 3.6
Classifier: Programming Language :: Python :: 3.7
Classifier: Programming Language :: Python :: 3.8
Classifier: Programming Language :: Python :: 3.9
Classifier: Programming Language :: Python :: 3.10
Requires-Dist: Topsis-Paavan-102003738
